byper/__init__.py
byper/constants/__init__.py
byper/core/__init__.py
byper/core/commands.py
byper/core/environment.py
byper/core/installation.py
byper/core/lockfile.py
byper/core/manifest.py
byper/utils/__init__.py
byper/utils/logger.py
byper-1.0.1.dist-info/METADATA
byper-1.0.1.dist-info/WHEEL
byper-1.0.1.dist-info/entry_points.txt
byper-1.0.1.dist-info/top_level.txt
byper-1.0.1.dist-info/RECORD
