Metadata-Version: 2.4
Name: byper
Version: 1.0.1
Summary: byper local dev package
Requires-Dist: pyyaml==6.0.1
Requires-Dist: ruamel.yaml==0.17.21
Requires-Dist: colorama==0.4.6
Requires-Dist: installer==0.7.0
Requires-Dist: packaging==24.0
Requires-Dist: jinja2==3.1.6
Requires-Dist: build==1.2.2.post1
Requires-Dist: twine==6.1.0
